README.md
setup.py
ezreal/__init__.py
ezreal/__main__.py
ezreal.egg-info/PKG-INFO
ezreal.egg-info/SOURCES.txt
ezreal.egg-info/dependency_links.txt
ezreal.egg-info/requires.txt
ezreal.egg-info/top_level.txt
ezreal/core/__init__.py
ezreal/core/summoner.py
ezreal/utils/__init__.py
ezreal/utils/common_utils.py
ezreal/utils/db_utils.py